odoo/addons/cooperator/README.rst
odoo/addons/cooperator/__init__.py
odoo/addons/cooperator/__manifest__.py
odoo/addons/cooperator/data/data.xml
odoo/addons/cooperator/data/mail_template_data.xml
odoo/addons/cooperator/demo/coop.xml
odoo/addons/cooperator/demo/users.xml
odoo/addons/cooperator/i18n/ca.po
odoo/addons/cooperator/i18n/ca_ES.po
odoo/addons/cooperator/i18n/cooperator.pot
odoo/addons/cooperator/i18n/de.po
odoo/addons/cooperator/i18n/de_DE.po
odoo/addons/cooperator/i18n/es.po
odoo/addons/cooperator/i18n/fr.po
odoo/addons/cooperator/i18n/fr_BE.po
odoo/addons/cooperator/i18n/it.po
odoo/addons/cooperator/i18n/nl_BE.po
odoo/addons/cooperator/i18n/pt_BR.po
odoo/addons/cooperator/migrations/16.0.1.0.0/post-migration.py
odoo/addons/cooperator/migrations/16.0.1.0.0/pre-migration.py
odoo/addons/cooperator/models/__init__.py
odoo/addons/cooperator/models/account_chart_template.py
odoo/addons/cooperator/models/account_journal.py
odoo/addons/cooperator/models/account_move.py
odoo/addons/cooperator/models/account_move_line.py
odoo/addons/cooperator/models/cooperative_membership.py
odoo/addons/cooperator/models/mail_template.py
odoo/addons/cooperator/models/operation_request.py
odoo/addons/cooperator/models/product_template.py
odoo/addons/cooperator/models/res_company.py
odoo/addons/cooperator/models/res_config_settings.py
odoo/addons/cooperator/models/res_partner.py
odoo/addons/cooperator/models/share_line.py
odoo/addons/cooperator/models/share_type.py
odoo/addons/cooperator/models/subscription_register.py
odoo/addons/cooperator/models/subscription_request.py
odoo/addons/cooperator/readme/CONTRIBUTORS.rst
odoo/addons/cooperator/readme/DESCRIPTION.rst
odoo/addons/cooperator/readme/HISTORY.rst
odoo/addons/cooperator/readme/ROADMAP.rst
odoo/addons/cooperator/readme/USAGE.rst
odoo/addons/cooperator/report/__init__.py
odoo/addons/cooperator/report/account_invoice_report.py
odoo/addons/cooperator/report/layout.xml
odoo_addon_cooperator-16.0.1.2.4.1.dist-info/METADATA
odoo_addon_cooperator-16.0.1.2.4.1.dist-info/WHEEL
odoo_addon_cooperator-16.0.1.2.4.1.dist-info/top_level.txt
odoo_addon_cooperator-16.0.1.2.4.1.dist-info/RECORD
